FernetKeyVault/__init__.py
FernetKeyVault/database_vault.py
FernetKeyVault/encryption_manager.py
FernetKeyVault/key_loader.py
fernetkeyvault-1.0.7.dist-info/METADATA
fernetkeyvault-1.0.7.dist-info/WHEEL
fernetkeyvault-1.0.7.dist-info/RECORD
