Metadata-Version: 2.4
Name: FernetKeyVault
Version: 1.0.7
Summary: A simple Python SQLite3-based key-value storage vault
Project-URL: Homepage, https://github.com/kvcrajan/FernetKeyVault
Project-URL: Bug Tracker, https://github.com/kvcrajan/FernetKeyVault/issues
Requires-Python: >=3.13.5
Requires-Dist: cryptography>=45.0.5
Requires-Dist: hatchling>=1.27.0
Provides-Extra: test
Requires-Dist: pytest-cov>=6.2.1; extra == 'test'
Requires-Dist: pytest>=8.4.1; extra == 'test'
